havedocker/Docker.py
havedocker/DockerError.py
havedocker/__init__.py
havedocker-0.1.3.7.dist-info/LICENSE
havedocker-0.1.3.7.dist-info/METADATA
havedocker-0.1.3.7.dist-info/WHEEL
havedocker-0.1.3.7.dist-info/top_level.txt
havedocker-0.1.3.7.dist-info/RECORD
