Metadata-Version: 2.1
Name: havedocker
Version: 0.1.3.7
Summary: Additional version based on 0.1.3.6 version
Home-page: https://github.com/haitanghuadeng
Author: haitanghuadeng
Author-email: 491609917@qq.com
License: UNKNOWN
Platform: UNKNOWN
Classifier: Programming Language :: Python :: 3
Classifier: License :: OSI Approved :: MIT License
Classifier: Operating System :: OS Independent
Classifier: Programming Language :: Python :: 3 :: Only
Classifier: Programming Language :: Python :: 3.6
Classifier: Programming Language :: Python :: 3.7
